{
  "Name": "Actions Abstract",
  "Words": [
    { "english": "solve", "italian": "risolvere", "learned": false, "done": false },
    { "english": "grow", "italian": "crescere", "learned": false, "done": false },
    { "english": "plan", "italian": "pianificare", "learned": false, "done": false },
    { "english": "decide", "italian": "decidere", "learned": false, "done": false },
    { "english": "increase", "italian": "aumentare", "learned": false, "done": false },
    { "english": "decrease", "italian": "diminuire", "learned": false, "done": false },
    { "english": "thrive", "italian": "prosperare", "learned": false, "done": false },
    { "english": "wait", "italian": "aspaterre", "learned": false, "done": false },
    { "english": "find", "italian": "trovare", "learned": false, "done": false },
    { "english": "lose", "italian": "perdere", "learned": false, "done": false },
    { "english": "improve", "italian": "migliorare", "learned": false, "done": false },
    { "english": "stay", "italian": "stare", "learned": false, "done": false },
    { "english": "leave", "italian": "lasciare", "learned": false, "done": false },
    { "english": "follow", "italian": "seguire", "learned": false, "done": false },
    { "english": "search / look for", "italian": "cercare", "learned": false, "done": false },
    { "english": "search", "italian": "recercare", "learned": false, "done": false },
    { "english": "provide", "italian": "fornire", "learned": false, "done": false },
    { "english": "use", "italian": "usare", "learned": false, "done": false },
    { "english": "succeed", "italian": "riuscire", "learned": false, "done": false },
    { "english": "try / attempt", "italian": "tentare", "learned": false, "done": false },
    { "english": "become", "italian": "diventare", "learned": false, "done": false },
    { "english": "help / assist", "italian": "aiutare", "learned": false, "done": false },
    { "english": "maintain", "italian": "mantere", "learned": false, "done": false },
    { "english": "start", "italian": "cominciare", "learned": false, "done": false },
    { "english": "stop", "italian": "fermare", "learned": false, "done": false },
    { "english": "begin", "italian": "iniziare", "learned": false, "done": false },
    { "english": "end", "italian": "finire", "learned": false, "done": false },
    { "english": "teach", "italian": "insegnare", "learned": false, "done": false },
    { "english": "change", "italian": "cambiare", "learned": false, "done": false },
    { "english": "advise", "italian": "consigliare", "learned": false, "done": false },
    { "english": "live", "italian": "abitare", "learned": false, "done": false },
    { "english": "promise", "italian": "promettere", "learned": false, "done": false },
    { "english": "happen", "italian": "succedere", "learned": false, "done": false },
    { "english": "occur", "italian": "accedere", "learned": false, "done": false },
    { "english": "avoid", "italian": "evitare", "learned": false, "done": false },
    { "english": "rent", "italian": "affittare", "learned": false, "done": false },
    { "english": "seem", "italian": "sembrare", "learned": false, "done": false },
    { "english": "share", "italian": "condividere", "learned": false, "done": false },
    { "english": "try", "italian": "provare", "learned": false, "done": false }
  ]
}
