{
  "Name": "Body",
  "Words": [
    { "english": "head", "italian": "testa", "learned": false, "done": false },
    { "english": "face", "italian": "viso", "learned": false, "done": false },
    { "english": "eye", "italian": "occhio", "learned": false, "done": false },
    { "english": "ear", "italian": "orecchio", "learned": false, "done": false },
    { "english": "nose", "italian": "naso", "learned": false, "done": false },
    { "english": "mouth", "italian": "bocca", "learned": false, "done": false },
    { "english": "lip", "italian": "labbro", "learned": false, "done": false },
    { "english": "tooth", "italian": "dente", "learned": false, "done": false },
    { "english": "tongue", "italian": "lingua", "learned": false, "done": false },
    { "english": "neck", "italian": "collo", "learned": false, "done": false },
    { "english": "shoulder", "italian": "spalla", "learned": false, "done": false },
    { "english": "arm", "italian": "braccio", "learned": false, "done": false },
    { "english": "breast", "italian": "seno", "learned": false, "done": false },
    { "english": "elbow", "italian": "gomito", "learned": false, "done": false },
    { "english": "wrist", "italian": "polso", "learned": false, "done": false },
    { "english": "hand", "italian": "mano", "learned": false, "done": false },
    { "english": "finger", "italian": "dito", "learned": false, "done": false },
    { "english": "thumb", "italian": "pollice", "learned": false, "done": false },
    { "english": "chest", "italian": "petto", "learned": false, "done": false },
    { "english": "back", "italian": "schiena", "learned": false, "done": false },
    { "english": "waist", "italian": "vita", "learned": false, "done": false },
    { "english": "belly", "italian": "pancia", "learned": false, "done": false },
    { "english": "hip", "italian": "anca", "learned": false, "done": false },
    { "english": "leg", "italian": "gamba", "learned": false, "done": false },
    { "english": "keel", "italian": "gola", "learned": false, "done": false },
    { "english": "knee", "italian": "ginocchio", "learned": false, "done": false },
    { "english": "ankle", "italian": "caviglia", "learned": false, "done": false },
    { "english": "foot", "italian": "piede", "learned": false, "done": false },
    { "english": "toe", "italian": "dito del piede", "learned": false, "done": false },
    { "english": "heel", "italian": "tallone", "learned": false, "done": false },
    { "english": "sole", "italian": "pavimento plantare", "learned": false, "done": false },
    { "english": "nail", "italian": "unghia", "learned": false, "done": false },
    { "english": "brain", "italian": "cervello", "learned": false, "done": false },
    { "english": "breath", "italian": "respiro", "learned": false, "done": false },
    { "english": "kiss", "italian": "bacio", "learned": false, "done": false },
    { "english": "mind", "italian": "mente", "learned": false, "done": false },
    { "english": "soul", "italian": "anima", "learned": false, "done": false },
    { "english": "body", "italian": "corpo", "learned": false, "done": false },
    { "english": "body", "italian": "corpo", "learned": false, "done": false },
    { "english": "hair", "italian": "capelli", "learned": false, "done": false }
  ]
}
